pydistrib/__init__.py
pydistrib/atomic_counter.py
pydistrib/server.py
pydistrib/slave.py
pydistrib/tests/TestServer.py
pydistrib-0.0.4.dist-info/LICENSE
pydistrib-0.0.4.dist-info/WHEEL
pydistrib-0.0.4.dist-info/METADATA
pydistrib-0.0.4.dist-info/RECORD
